[{
  "_id": {
    "$oid": "669be66dbce6b3cb0c48b517"
  },
  "episode": "Episode 885 886 887",
  "title": "A TERRIFYING ALLIANCE!",
  "first-link": "https://streamable.com/krh9jf",
  "second-link": "https://drive.google.com/file/d/1dFO9yrrKx11LLiBo_lICcVH_WRdQyx-O/view?usp=drive_link",
  "thumbnail": "https://i.imgur.com/Ee3X1qq.jpg"
},
{
  "_id": {
    "$oid": "669be696bce6b3cb0c48b518"
  },
  "episode": "Episode 879 880 881",
  "title": "HIS BOUNTY IS WHAT???",
  "first-link": "https://streamable.com/4eoc3l",
  "second-link": "https://drive.google.com/file/d/15dFejOr1zrgZf_w4bHVc0t6u-OfPU4BB/view?usp=drive_link",
  "thumbnail": "https://i.imgur.com/OqKFWFa.jpg"
},
{
  "_id": {
    "$oid": "669be6afbce6b3cb0c48b519"
  },
  "episode": "Episode 882 883 884",
  "title": "A NEW ADMIRAL INTRODUCED?",
  "first-link": "https://streamable.com/caoit8",
  "second-link": "https://drive.google.com/file/d/1CHlbaW_JBWO60K4PfdY7M8U_PfONcNyn/view?usp=drive_link",
  "thumbnail": "https://i.imgur.com/HYMGVij.jpg"
},
{
  "_id": {
    "$oid": "669be6cdbce6b3cb0c48b51a"
  },
  "episode": "Episode 888 889 890",
  "title": "THE TRUE MASTERMIND??",
  "first-link": "https://streamable.com/gtcxgp",
  "second-link": "https://drive.google.com/file/d/123D-eSFsw_OGrB7vI2bVRYiT17fppE9W/view?usp=drive_link",
  "thumbnail": "https://i.imgur.com/YFMut4R.jpg"
},
{
  "_id": {
    "$oid": "669be6edbce6b3cb0c48b51b"
  },
  "episode": "Episode 891 892 893",
  "title": "WANO IS SO BEAUTIFUL!!",
  "first-link": "https://streamable.com/xvagln",
  "second-link": "https://drive.google.com/file/d/1t9p4V8Hz0ZSrvHUyqRSrD4K0Yp3BtI1z/view?usp=drive_link",
  "thumbnail": "https://i.imgur.com/bNpUIwW.jpg"
}]